CHANGES.txt
LICENSE.txt
MANIFEST.in
README.txt
bootstrap.py
buildout.cfg
setup.py
pojson/__init__.py
pojson/convert.py
pojson/frontend.py
pojson/main.py
pojson/test_convert.py
pojson/test_frontend.py
pojson.egg-info/PKG-INFO
pojson.egg-info/SOURCES.txt
pojson.egg-info/dependency_links.txt
pojson.egg-info/entry_points.txt
pojson.egg-info/not-zip-safe
pojson.egg-info/requires.txt
pojson.egg-info/top_level.txt
pojson/testdata/ko.po
pojson/testdata/nl.po
pojson/testdata/babel_messages/ko/LC_MESSAGES/messages.po
pojson/testdata/babel_messages/nl/LC_MESSAGES/messages.po