Metadata-Version: 1.0
Name: pojson
Version: 0.6
Summary: Convert PO files to JSON
Home-page: https://bitbucket.org/obviel/pojson
Author: Martijn Faassen
Author-email: faassen@startifact.com
License: BSD
Keywords: PO i18n internationalisation JSON gettext obviel
Platform: UNKNOWN
